[
  {
    "claimID": "7MD-KS92-FB93-B",
    "workplaceID": "B02944934",
    "claimType": "60",
    "isPaymentPlan": true,
    "status": "approved",
    "createdDate": "2025-01-31T00:06:28.462Z",
    "createdBy": "lena.caldwell@evergreencare.com",
    "submissions": [
      {
        "submitter": "lena.caldwell@evergreencare.com",
        "submittedDate": "2025-03-01T07:53:32.066Z",
        "trainingCode": "501/1146/2",
        "startDate": "2025-01-25T09:54:13.322Z",
        "costDate": "2024-08-18T14:35:08.968Z",
        "evidenceOfPayment": [
          "Bankstatement-scenario260.png",
          "InvoicePP-scenario260.png"
        ],
        "evidenceOfPaymentReview": {
          "outcome": "pass",
          "note": null,
          "paymentPlan": "yes",
          "costPerLearner": 120
        },
        "processedDate": "2025-03-14T06:15:38.665Z",
        "processedBy": "Allan Connelly",
        "learners": [
          {
            "slotID": "1",
            "learnerID": "BF 73 4F 97 L",
            "completionDate": null,
            "evidenceOfCompletion": null,
            "evidenceOfCompletionReview": {
              "outcome": null,
              "note": null
            }
          },
          {
            "slotID": "2",
            "learnerID": "LM 89 7F 48 J",
            "completionDate": null,
            "evidenceOfCompletion": null,
            "evidenceOfCompletionReview": {
              "outcome": null,
              "note": null
            }
          },
          {
            "slotID": "3",
            "learnerID": "NX 76 8F 30 D",
            "completionDate": null,
            "evidenceOfCompletion": null,
            "evidenceOfCompletionReview": {
              "outcome": null,
              "note": null
            }
          },
          {
            "slotID": "4",
            "learnerID": "ZX 51 96 87 D",
            "completionDate": null,
            "evidenceOfCompletion": null,
            "evidenceOfCompletionReview": {
              "outcome": null,
              "note": null
            }
          },
          {
            "slotID": "5",
            "learnerID": "HB 78 2F 15 O",
            "completionDate": null,
            "evidenceOfCompletion": null,
            "evidenceOfCompletionReview": {
              "outcome": null,
              "note": null
            }
          },
          {
            "slotID": "6",
            "learnerID": "LE 09 5F 94 M",
            "completionDate": null,
            "evidenceOfCompletion": null,
            "evidenceOfCompletionReview": {
              "outcome": null,
              "note": null
            }
          }
        ],
        "sharedCompletionDate": false
      },
      {
        "submitter": "lena.caldwell@evergreencare.com",
        "submittedDate": "2025-02-01T07:53:32.066Z",
        "trainingCode": "501/1146/2",
        "startDate": "2025-01-25T09:54:13.322Z",
        "costDate": "2024-08-18T14:35:08.968Z",
        "evidenceOfPayment": [
          "Bankstatement-scenario260.png"
        ],
        "evidenceOfPaymentReview": {
          "outcome": "queried",
          "note": "The payment evidence is insufficient to show you paid for this training. Please add additional evidence.",
          "paymentPlan": null,
          "costPerLearner": null
        },
        "processedDate": "2025-02-24T06:15:38.665Z",
        "processedBy": "Allan Connelly",
        "learners": [
          {
            "slotID": "1",
            "learnerID": "BF 73 4F 97 L",
            "completionDate": null,
            "evidenceOfCompletion": null,
            "evidenceOfCompletionReview": {
              "outcome": null,
              "note": null
            }
          },
          {
            "slotID": "2",
            "learnerID": "LM 89 7F 48 J",
            "completionDate": null,
            "evidenceOfCompletion": null,
            "evidenceOfCompletionReview": {
              "outcome": null,
              "note": null
            }
          },
          {
            "slotID": "3",
            "learnerID": "NX 76 8F 30 D",
            "completionDate": null,
            "evidenceOfCompletion": null,
            "evidenceOfCompletionReview": {
              "outcome": null,
              "note": null
            }
          },
          {
            "slotID": "4",
            "learnerID": "ZX 51 96 87 D",
            "completionDate": null,
            "evidenceOfCompletion": null,
            "evidenceOfCompletionReview": {
              "outcome": null,
              "note": null
            }
          },
          {
            "slotID": "5",
            "learnerID": "HB 78 2F 15 O",
            "completionDate": null,
            "evidenceOfCompletion": null,
            "evidenceOfCompletionReview": {
              "outcome": null,
              "note": null
            }
          },
          {
            "slotID": "6",
            "learnerID": "LE 09 5F 94 M",
            "completionDate": null,
            "evidenceOfCompletion": null,
            "evidenceOfCompletionReview": {
              "outcome": null,
              "note": null
            }
          }
        ],
        "sharedCompletionDate": false
      }
    ]
  },
  {
    "claimID": "7MD-KS92-FB93-C",
    "workplaceID": "B02944934",
    "claimType": "40",
    "isPaymentPlan": true,
    "status": "submitted",
    "createdDate": "2025-03-03T00:12:28.462Z",
    "createdBy": "lena.caldwell@evergreencare.com",
    "submissions": [
      {
        "submitter": "d.jones@evergreencare.com",
        "submittedDate": "2025-04-16T08:21:17.133Z",
        "trainingCode": "501/1146/2",
        "startDate": "2025-03-24T09:54:13.322Z",
        "costDate": "2025-03-01T03:16:00.448Z",
        "evidenceOfPayment": [
          "InvoicePP-scenario240.png",
          "BankstatementPP-scenario240.png"
        ],
        "evidenceOfPaymentReview": {
          "outcome": null,
          "note": null,
          "paymentPlan": null,
          "costPerLearner": null
        },
        "processedDate": null,
        "processedBy": null,
        "learners": [
          {
            "slotID": "1",
            "learnerID": "BF 73 4F 97 L",
            "completionDate": "2025-03-25T03:16:00.448Z",
            "evidenceOfCompletion": "certificate-orlandoPadberg.pdf",
            "evidenceOfCompletionReview": {
              "outcome": null,
              "note": null
            }
          },
          {
            "slotID": "2",
            "learnerID": "LM 89 7F 48 J",
            "completionDate": "2025-03-25T03:16:00.448Z",
            "evidenceOfCompletion": "certificate-orlandoPadberg.pdf",
            "evidenceOfCompletionReview": {
              "outcome": null,
              "note": null
            }
          },
          {
            "slotID": "3",
            "learnerID": "NX 76 8F 30 D",
            "completionDate": "2025-03-25T03:16:00.448Z",
            "evidenceOfCompletion": "certificate-orlandoPadberg.pdf",
            "evidenceOfCompletionReview": {
              "outcome": null,
              "note": null
            }
          },
          {
            "slotID": "4",
            "learnerID": "ZX 51 96 87 D",
            "completionDate": "2025-03-25T03:16:00.448Z",
            "evidenceOfCompletion": "certificate-orlandoPadberg.pdf",
            "evidenceOfCompletionReview": {
              "outcome": null,
              "note": null
            }
          },
          {
            "slotID": "6",
            "learnerID": "LE 09 5F 94 M",
            "completionDate": "2025-03-25T03:16:00.448Z",
            "evidenceOfCompletion": "certificate-orlandoPadberg.pdf",
            "evidenceOfCompletionReview": {
              "outcome": null,
              "note": null
            }
          }
        ],
        "sharedCompletionDate": false
      },
      {
        "submitter": "d.jones@evergreencare.com",
        "submittedDate": "2025-04-02T08:21:17.133Z",
        "trainingCode": "501/1146/2",
        "startDate": "2025-03-24T09:54:13.322Z",
        "costDate": "2025-04-01T03:16:00.448Z",
        "evidenceOfPayment": [
          "bankStatement1.pdf"
        ],
        "evidenceOfPaymentReview": {
          "outcome": "pass",
          "note": null,
          "paymentPlan": "yes",
          "costPerLearner": 120
        },
        "processedDate": "2025-04-14T06:15:38.665Z",
        "processedBy": "Allan Connelly",
        "learners": [
          {
            "slotID": "1",
            "learnerID": "BF 73 4F 97 L",
            "completionDate": "2025-03-25T03:16:00.448Z",
            "evidenceOfCompletion": "certificate001.pdf",
            "evidenceOfCompletionReview": {
              "outcome": "queried",
              "note": "The certificate doesn't match the learner, please upload the correct certificate."
            }
          },
          {
            "slotID": "2",
            "learnerID": "LM 89 7F 48 J",
            "completionDate": "2025-03-25T03:16:00.448Z",
            "evidenceOfCompletion": "certificate001.pdf",
            "evidenceOfCompletionReview": {
              "outcome": "queried",
              "note": "The certificate doesn't match the learner, please upload the correct certificate."
            }
          },
          {
            "slotID": "3",
            "learnerID": "NX 76 8F 30 D",
            "completionDate": "2025-03-25T03:16:00.448Z",
            "evidenceOfCompletion": "certificate001.pdf",
            "evidenceOfCompletionReview": {
              "outcome": "queried",
              "note": "The certificate doesn't match the learner, please upload the correct certificate."
            }
          },
          {
            "slotID": "4",
            "learnerID": "ZX 51 96 87 D",
            "completionDate": "2025-03-25T03:16:00.448Z",
            "evidenceOfCompletion": "certificate001.pdf",
            "evidenceOfCompletionReview": {
              "outcome": "queried",
              "note": "The certificate doesn't match the learner, please upload the correct certificate."
            }
          },
          {
            "slotID": "5",
            "learnerID": "HB 78 2F 15 O",
            "completionDate": "2025-03-25T03:16:00.448Z",
            "evidenceOfCompletion": "certificate001.pdf",
            "evidenceOfCompletionReview": {
              "outcome": "queried",
              "note": "The certificate doesn't match the learner, please upload the correct certificate."
            }
          },
          {
            "slotID": "6",
            "learnerID": "LE 09 5F 94 M",
            "completionDate": "2025-03-25T03:16:00.448Z",
            "evidenceOfCompletion": "certificate001.pdf",
            "evidenceOfCompletionReview": {
              "outcome": "queried",
              "note": "The certificate doesn't match the learner, please upload the correct certificate."
            }
          }
        ],
        "sharedCompletionDate": false
      }
    ]
  },
  {
    "claimID": "8LF-SJ43-JMS3-B",
    "workplaceID": "B02944934",
    "claimType": "60",
    "isPaymentPlan": null,
    "status": "submitted",
    "createdDate": "2024-05-24T21:55:08.777Z",
    "createdBy": "lena.caldwell@evergreencare.com",
    "submissions": [
      {
        "submitter": "lionel-lowel@evergreencare.co.uk",
        "submittedDate": "2025-03-03T07:43:14.557Z",
        "trainingCode": "601/1464/2",
        "startDate": "2024-08-08T11:45:01.732Z",
        "costDate": "2024-06-27T01:16:45.233Z",
        "evidenceOfPayment": [
          "bankstatementPP-scenario1.png",
          "InvoicePP-scenario1.png"
        ],
        "evidenceOfPaymentReview": {
          "outcome": null,
          "note": null,
          "paymentPlan": null,
          "costPerLearner": null
        },
        "processedDate": null,
        "processedBy": null,
        "learners": [
          {
            "slotID": "1",
            "learnerID": "LE 09 5F 94 M",
            "completionDate": null,
            "evidenceOfCompletion": null,
            "evidenceOfCompletionReview": {
              "outcome": null,
              "note": null
            }
          }
        ],
        "sharedCompletionDate": false
      },
      {
        "submitter": "lionel-lowel@evergreencare.co.uk",
        "submittedDate": "2025-02-07T07:43:14.557Z",
        "trainingCode": "601/1464/2",
        "startDate": "2024-08-08T11:45:01.732Z",
        "costDate": "2024-06-17T01:16:45.233Z",
        "evidenceOfPayment": [
          "bankStatement-august.pdf",
          "invoice1.pdf"
        ],
        "evidenceOfPaymentReview": {
          "outcome": "queried",
          "note": "The payment date doesn't match the payment evidence, please update.",
          "paymentPlan": null,
          "costPerLearner": null
        },
        "processedDate": "2025-02-12T07:43:14.557Z",
        "processedBy": "Flossie Gleaason",
        "learners": [
          {
            "slotID": "1",
            "learnerID": "LE 09 5F 94 M",
            "completionDate": null,
            "evidenceOfCompletion": null,
            "evidenceOfCompletionReview": {
              "outcome": null,
              "note": null
            }
          }
        ],
        "sharedCompletionDate": false
      }
    ]
  },
  {
    "claimID": "K2F-ALSM-SHJD-B",
    "workplaceID": "B02944934",
    "claimType": "60",
    "isPaymentPlan": true,
    "status": "approved",
    "createdDate": "2024-05-24T21:55:08.777Z",
    "createdBy": "lena.caldwell@evergreencare.com",
    "submissions": [
      {
        "submitter": "lionel-lowel@evergreencare.co.uk",
        "submittedDate": "2025-03-03T07:43:14.557Z",
        "trainingCode": "601/1464/2",
        "startDate": "2024-08-08T11:45:01.732Z",
        "costDate": "2024-06-27T01:16:45.233Z",
        "evidenceOfPayment": [
          "bankstatementPP-scenario1.png",
          "InvoicePP-scenario1.png"
        ],
        "evidenceOfPaymentReview": {
          "outcome": "pass",
          "note": null,
          "paymentPlan": "yes",
          "costPerLearner": 108
        },
        "processedDate": "2025-03-05T07:43:14.557Z",
        "processedBy": "Flossie Gleaason",
        "learners": [
          {
            "slotID": "1",
            "learnerID": "KZ 79 0F 13 Z",
            "completionDate": null,
            "evidenceOfCompletion": null,
            "evidenceOfCompletionReview": {
              "outcome": null,
              "note": null
            }
          },
          {
            "slotID": "2",
            "learnerID": "LE 09 5F 94 M",
            "completionDate": null,
            "evidenceOfCompletion": null,
            "evidenceOfCompletionReview": {
              "outcome": null,
              "note": null
            }
          }
        ],
        "sharedCompletionDate": false
      },
      {
        "submitter": "lionel-lowel@evergreencare.co.uk",
        "submittedDate": "2025-02-07T07:43:14.557Z",
        "trainingCode": "601/1464/2",
        "startDate": "2024-08-08T11:45:01.732Z",
        "costDate": "2024-06-17T01:16:45.233Z",
        "evidenceOfPayment": [
          "bankStatement-august.pdf",
          "invoice1.pdf"
        ],
        "evidenceOfPaymentReview": {
          "outcome": "queried",
          "note": "The payment date doesn't match the payment evidence, please update.",
          "paymentPlan": null,
          "costPerLearner": null
        },
        "processedDate": "2025-02-12T07:43:14.557Z",
        "processedBy": "Flossie Gleaason",
        "learners": [
          {
            "slotID": "1",
            "learnerID": "KZ 79 0F 13 Z",
            "completionDate": null,
            "evidenceOfCompletion": null,
            "evidenceOfCompletionReview": {
              "outcome": null,
              "note": null
            }
          },
          {
            "slotID": "2",
            "learnerID": "LE 09 5F 94 M",
            "completionDate": null,
            "evidenceOfCompletion": null,
            "evidenceOfCompletionReview": {
              "outcome": null,
              "note": null
            }
          }
        ],
        "sharedCompletionDate": false
      }
    ]
  },
  {
    "claimID": "3SH-I94K-JSND-B",
    "workplaceID": "B02944934",
    "claimType": "60",
    "isPaymentPlan": true,
    "status": "approved",
    "createdDate": "2025-01-01T00:06:28.462Z",
    "createdBy": "lena.caldwell@evergreencare.com",
    "submissions": [
      {
        "submitter": "lena.caldwell@evergreencare.com",
        "submittedDate": "2025-01-04T07:53:32.066Z",
        "trainingCode": "501/1146/2",
        "startDate": "2025-02-24T09:54:13.322Z",
        "costDate": "2024-10-18T14:35:08.968Z",
        "evidenceOfPayment": [
          "october-statement"
        ],
        "evidenceOfPaymentReview": {
          "outcome": "pass",
          "note": null,
          "paymentPlan": "yes",
          "costPerLearner": 108
        },
        "processedDate": "2025-02-03T06:15:38.665Z",
        "processedBy": "Allan Connelly",
        "learners": [
          {
            "slotID": "1",
            "learnerID": "NX 76 8F 30 D",
            "completionDate": null,
            "evidenceOfCompletion": null,
            "evidenceOfCompletionReview": {
              "outcome": null,
              "note": null
            }
          }
        ],
        "sharedCompletionDate": false
      },
      {
        "submitter": "lena.caldwell@evergreencare.com",
        "submittedDate": "2025-01-03T07:53:32.066Z",
        "trainingCode": "501/1146/2",
        "startDate": "2025-02-24T09:54:13.322Z",
        "costDate": "2024-10-16T14:35:08.968Z",
        "evidenceOfPayment": [
          "october-statement"
        ],
        "evidenceOfPaymentReview": {
          "outcome": "queried",
          "note": "The cost date doesn't match the payment evidence",
          "paymentPlan": null,
          "costPerLearner": null
        },
        "processedDate": "2025-02-02T06:15:38.665Z",
        "processedBy": "Allan Connelly",
        "learners": [
          {
            "slotID": "1",
            "learnerID": "NX 76 8F 30 D",
            "completionDate": null,
            "evidenceOfCompletion": null,
            "evidenceOfCompletionReview": {
              "outcome": null,
              "note": null
            }
          }
        ],
        "sharedCompletionDate": false
      }
    ]
  },
  {
    "claimID": "3SH-I94K-JSND-C",
    "workplaceID": "B02944934",
    "claimType": "40",
    "isPaymentPlan": true,
    "status": "submitted",
    "createdDate": "2025-02-03T00:12:28.462Z",
    "createdBy": "lena.caldwell@evergreencare.com",
    "submissions": [
      {
        "submitter": "d.jones@evergreencare.com",
        "submittedDate": "2025-03-06T08:21:17.133Z",
        "trainingCode": "501/1146/2",
        "startDate": "2025-02-24T09:54:13.322Z",
        "costDate": "2025-03-01T03:16:00.448Z",
        "evidenceOfPayment": [
          "invoice1.pdf",
          "bankStatement1.pdf"
        ],
        "evidenceOfPaymentReview": {
          "outcome": null,
          "note": null,
          "paymentPlan": null,
          "costPerLearner": null
        },
        "processedDate": null,
        "processedBy": null,
        "learners": [
          {
            "slotID": "1",
            "learnerID": "NX 76 8F 30 D",
            "completionDate": "2025-02-27T03:16:00.448Z",
            "evidenceOfCompletion": "certificate-orlandoPadberg.pdf",
            "evidenceOfCompletionReview": {
              "outcome": null,
              "note": null
            }
          }
        ],
        "sharedCompletionDate": false
      }
    ]
  },
  {
    "claimID": "SC1-74V3-JSK4-A",
    "workplaceID": "B02944934",
    "claimType": "100",
    "isPaymentPlan": null,
    "status": "inProgress",
    "createdDate": "2024-07-11T03:36:53.621Z",
    "createdBy": "lena.caldwell@evergreencare.com",
    "submissions": [
      {
        "submitter": "jasper.holloway@evergreencare.com",
        "submittedDate": "2025-02-01T11:52:30.850Z",
        "trainingCode": "IMLM",
        "startDate": "2024-07-21T03:36:53.621Z",
        "costDate": "2024-09-25T12:05:18.831Z",
        "evidenceOfPayment": [
          "invoice-212.pdf",
          "bank-statement-212.pdf"
        ],
        "evidenceOfPaymentReview": {
          "outcome": "pass",
          "note": null,
          "paymentPlan": null,
          "costPerLearner": "40"
        },
        "processedDate": null,
        "processedBy": null,
        "learners": [
          {
            "slotID": "1",
            "learnerID": "KZ 79 0F 13 Z",
            "completionDate": "2024-10-02T11:52:30.850Z",
            "evidenceOfCompletion": "certificate-313.pdf",
            "evidenceOfCompletionReview": {
              "outcome": "queried",
              "note": "The certificate doesn't match the completion date. Please enter the correct completion date."
            }
          },
          {
            "slotID": "2",
            "learnerID": "LE 09 5F 94 M",
            "completionDate": "2024-10-02T11:52:30.850Z",
            "evidenceOfCompletion": "certificate-313.pdf",
            "evidenceOfCompletionReview": {
              "outcome": "queried",
              "note": "The certificate doesn't match the completion date. Please enter the correct completion date."
            }
          },
          {
            "slotID": "3",
            "learnerID": "HB 78 2F 15 O",
            "completionDate": "2024-10-02T11:52:30.850Z",
            "evidenceOfCompletion": "certificate-313.pdf",
            "evidenceOfCompletionReview": {
              "outcome": "queried",
              "note": "The certificate doesn't match the completion date. Please enter the correct completion date."
            }
          },
          {
            "slotID": "4",
            "learnerID": "ZX 51 96 87 D",
            "completionDate": "2024-10-02T11:52:30.850Z",
            "evidenceOfCompletion": "certificate-313.pdf",
            "evidenceOfCompletionReview": {
              "outcome": "queried",
              "note": "The certificate doesn't match the completion date. Please enter the correct completion date."
            }
          },
          {
            "slotID": "5",
            "learnerID": "NX 76 8F 30 D",
            "completionDate": "2024-10-02T11:52:30.850Z",
            "evidenceOfCompletion": "certificate-212.pdf",
            "evidenceOfCompletionReview": {
              "outcome": "pass",
              "note": null
            }
          },
          {
            "slotID": "6",
            "learnerID": "LM 89 7F 48 J",
            "completionDate": "2024-10-02T11:52:30.850Z",
            "evidenceOfCompletion": "certificate-212.pdf",
            "evidenceOfCompletionReview": {
              "outcome": "pass",
              "note": null
            }
          },
          {
            "slotID": "7",
            "learnerID": "BF 73 4F 97 L",
            "completionDate": "2024-10-02T11:52:30.850Z",
            "evidenceOfCompletion": "certificate-212.pdf",
            "evidenceOfCompletionReview": {
              "outcome": null,
              "note": null
            }
          },
          {
            "slotID": "8",
            "learnerID": "KX 89 9F 87 K",
            "completionDate": "2024-10-02T11:52:30.850Z",
            "evidenceOfCompletion": "certificate-212.pdf",
            "evidenceOfCompletionReview": {
              "outcome": "pass",
              "note": null
            }
          },
          {
            "slotID": "9",
            "learnerID": "OA 78 8F 31 V",
            "completionDate": "2024-10-02T11:52:30.850Z",
            "evidenceOfCompletion": "certificate-212.pdf",
            "evidenceOfCompletionReview": {
              "outcome": "pass",
              "note": null
            }
          },
          {
            "slotID": "10",
            "learnerID": "KQ 01 7F 72 D",
            "completionDate": "2024-10-02T11:52:30.850Z",
            "evidenceOfCompletion": "certificate-212.pdf",
            "evidenceOfCompletionReview": {
              "outcome": "pass",
              "note": null
            }
          },
          {
            "slotID": "11",
            "learnerID": "GR 03 6F 10 P",
            "completionDate": "2024-10-02T11:52:30.850Z",
            "evidenceOfCompletion": "certificate-212.pdf",
            "evidenceOfCompletionReview": {
              "outcome": "pass",
              "note": null
            }
          },
          {
            "slotID": "12",
            "learnerID": "JU 91 7F 75 P",
            "completionDate": "2024-10-02T11:52:30.850Z",
            "evidenceOfCompletion": "certificate-212.pdf",
            "evidenceOfCompletionReview": {
              "outcome": "pass",
              "note": null
            }
          },
          {
            "slotID": "13",
            "learnerID": "CM 61 1F 12 E",
            "completionDate": "2024-10-02T11:52:30.850Z",
            "evidenceOfCompletion": "certificate-212.pdf",
            "evidenceOfCompletionReview": {
              "outcome": "pass",
              "note": null
            }
          },
          {
            "slotID": "14",
            "learnerID": "VL 10 7F 63 E",
            "completionDate": "2024-10-02T11:52:30.850Z",
            "evidenceOfCompletion": "certificate-212.pdf",
            "evidenceOfCompletionReview": {
              "outcome": "pass",
              "note": null
            }
          },
          {
            "slotID": "15",
            "learnerID": "ZH 56 2F 40 Y",
            "completionDate": "2024-10-02T11:52:30.850Z",
            "evidenceOfCompletion": "certificate-212.pdf",
            "evidenceOfCompletionReview": {
              "outcome": "pass",
              "note": null
            }
          },
          {
            "slotID": "16",
            "learnerID": "UG 66 2F 97 F",
            "completionDate": "2024-10-02T11:52:30.850Z",
            "evidenceOfCompletion": "certificate-212.pdf",
            "evidenceOfCompletionReview": {
              "outcome": null,
              "note": null
            }
          },
          {
            "slotID": "17",
            "learnerID": "CW 99 7F 83 J",
            "completionDate": "2024-10-02T11:52:30.850Z",
            "evidenceOfCompletion": "certificate-212.pdf",
            "evidenceOfCompletionReview": {
              "outcome": "pass",
              "note": null
            }
          },
          {
            "slotID": "18",
            "learnerID": "AL 82 2F 62 C",
            "completionDate": "2024-10-02T11:52:30.850Z",
            "evidenceOfCompletion": "certificate-312.pdf",
            "evidenceOfCompletionReview": {
              "outcome": "pass",
              "note": null
            }
          },
          {
            "slotID": "19",
            "learnerID": "HM 27 9F 18 T",
            "completionDate": "2024-10-02T11:52:30.850Z",
            "evidenceOfCompletion": "certificate-312.pdf",
            "evidenceOfCompletionReview": {
              "outcome": "pass",
              "note": null
            }
          }
        ],
        "sharedCompletionDate": true
      },
      {
        "submitter": "jasper.holloway@evergreencare.com",
        "submittedDate": "2024-10-07T11:52:30.850Z",
        "trainingCode": "DLEDI",
        "startDate": "2024-07-21T03:36:53.621Z",
        "costDate": "2024-09-23T12:05:18.831Z",
        "evidenceOfPayment": [
          "sept-bankstatement.png"
        ],
        "evidenceOfPaymentReview": {
          "outcome": "queried",
          "note": "The date of payment in the payment evidence did not match the payment date given in the claim. Update the payment date or provide the correct evidence",
          "paymentPlan": null,
          "costPerLearner": null
        },
        "processedDate": "2025-01-20T11:52:30.850Z",
        "processedBy": "Flossie Gleason",
        "learners": [
          {
            "slotID": "5",
            "learnerID": "NX 76 8F 30 D",
            "completionDate": "2024-10-02T11:52:30.850Z",
            "evidenceOfCompletion": "certificate-braxtonSchiller.pdf",
            "evidenceOfCompletionReview": {
              "outcome": "queried",
              "note": "The learner name in the completion certificate does not match the learner given in the claim. Need to provide the correct certificate for the correct learner."
            }
          },
          {
            "slotID": "4",
            "learnerID": "ZX 51 96 87 D",
            "completionDate": "2024-10-02T11:52:30.850Z",
            "evidenceOfCompletion": "certificate-braxtonSchiller.pdf",
            "evidenceOfCompletionReview": {
              "outcome": "queried",
              "note": "The learner name in the completion certificate does not match the learner given in the claim. Need to provide the correct certificate for the correct learner."
            }
          },
          {
            "slotID": "3",
            "learnerID": "HB 78 2F 15 O",
            "completionDate": "2024-10-02T11:52:30.850Z",
            "evidenceOfCompletion": "certificate-braxtonSchiller.pdf",
            "evidenceOfCompletionReview": {
              "outcome": "queried",
              "note": "The learner name in the completion certificate does not match the learner given in the claim. Need to provide the correct certificate for the correct learner."
            }
          },
          {
            "slotID": "7",
            "learnerID": "BF 73 4F 97 L",
            "completionDate": "2024-10-02T11:52:30.850Z",
            "evidenceOfCompletion": "certificate-braxtonSchiller.pdf",
            "evidenceOfCompletionReview": {
              "outcome": "queried",
              "note": "The learner name in the completion certificate does not match the learner given in the claim. Need to provide the correct certificate for the correct learner."
            }
          },
          {
            "slotID": "2",
            "learnerID": "LE 09 5F 94 M",
            "completionDate": "2024-10-02T11:52:30.850Z",
            "evidenceOfCompletion": "certificate-braxtonSchiller.pdf",
            "evidenceOfCompletionReview": {
              "outcome": "queried",
              "note": "The learner name in the completion certificate does not match the learner given in the claim. Need to provide the correct certificate for the correct learner."
            }
          }
        ],
        "sharedCompletionDate": true
      }
    ]
  },
  {
    "claimID": "ASK-74V3-JSK4-A",
    "workplaceID": "B02944934",
    "claimType": "100",
    "isPaymentPlan": null,
    "status": "submitted",
    "createdDate": "2024-07-11T03:36:53.621Z",
    "createdBy": "lena.caldwell@evergreencare.com",
    "submissions": [
      {
        "submitter": "jasper.holloway@evergreencare.com",
        "submittedDate": "2025-02-01T11:52:30.850Z",
        "trainingCode": "DLEDI",
        "startDate": "2024-07-21T03:36:53.621Z",
        "costDate": "2024-09-25T12:05:18.831Z",
        "evidenceOfPayment": [
          "sept-bankstatement.png"
        ],
        "evidenceOfPaymentReview": {
          "outcome": null,
          "note": null,
          "paymentPlan": null,
          "costPerLearner": null
        },
        "processedDate": null,
        "processedBy": null,
        "learners": [
          {
            "slotID": "1",
            "learnerID": "NX 76 8F 30 D",
            "completionDate": "2024-10-02T11:52:30.850Z",
            "evidenceOfCompletion": "certificate-braxtonSchiller.pdf",
            "evidenceOfCompletionReview": {
              "outcome": null,
              "note": null
            }
          },
          {
            "slotID": "2",
            "learnerID": "ZX 51 96 87 D",
            "completionDate": "2024-10-02T11:52:30.850Z",
            "evidenceOfCompletion": "certificate-braxtonSchiller.pdf",
            "evidenceOfCompletionReview": {
              "outcome": null,
              "note": null
            }
          },
          {
            "slotID": "3",
            "learnerID": "HB 78 2F 15 O",
            "completionDate": "2024-10-02T11:52:30.850Z",
            "evidenceOfCompletion": "certificate-braxtonSchiller.pdf",
            "evidenceOfCompletionReview": {
              "outcome": null,
              "note": null
            }
          },
          {
            "slotID": "4",
            "learnerID": "BF 73 4F 97 L",
            "completionDate": "2024-10-02T11:52:30.850Z",
            "evidenceOfCompletion": "certificate-braxtonSchiller.pdf",
            "evidenceOfCompletionReview": {
              "outcome": null,
              "note": null
            }
          },
          {
            "slotID": "5",
            "learnerID": "LE 09 5F 94 M",
            "completionDate": "2024-10-02T11:52:30.850Z",
            "evidenceOfCompletion": "certificate-braxtonSchiller.pdf",
            "evidenceOfCompletionReview": {
              "outcome": null,
              "note": null
            }
          }
        ],
        "sharedCompletionDate": false
      },
      {
        "submitter": "jasper.holloway@evergreencare.com",
        "submittedDate": "2024-10-07T11:52:30.850Z",
        "trainingCode": "DLEDI",
        "startDate": "2024-07-21T03:36:53.621Z",
        "costDate": "2024-09-23T12:05:18.831Z",
        "evidenceOfPayment": [
          "sept-bankstatement.png"
        ],
        "evidenceOfPaymentReview": {
          "outcome": "queried",
          "note": "The date of payment in the payment evidence did not match the payment date given in the claim. Update the payment date or provide the correct evidence",
          "paymentPlan": null,
          "costPerLearner": null
        },
        "processedDate": "2025-01-20T11:52:30.850Z",
        "processedBy": "Flossie Gleason",
        "learners": [
          {
            "slotID": "1",
            "learnerID": "NX 76 8F 30 D",
            "completionDate": "2024-10-02T11:52:30.850Z",
            "evidenceOfCompletion": "certificate-braxtonSchiller.pdf",
            "evidenceOfCompletionReview": {
              "outcome": "queried",
              "note": "The learner name in the completion certificate does not match the learner given in the claim. Need to provide the correct certificate for the correct learner."
            }
          },
          {
            "slotID": "2",
            "learnerID": "ZX 51 96 87 D",
            "completionDate": "2024-10-02T11:52:30.850Z",
            "evidenceOfCompletion": "certificate-braxtonSchiller.pdf",
            "evidenceOfCompletionReview": {
              "outcome": "queried",
              "note": "The learner name in the completion certificate does not match the learner given in the claim. Need to provide the correct certificate for the correct learner."
            }
          },
          {
            "slotID": "3",
            "learnerID": "HB 78 2F 15 O",
            "completionDate": "2024-10-02T11:52:30.850Z",
            "evidenceOfCompletion": "certificate-braxtonSchiller.pdf",
            "evidenceOfCompletionReview": {
              "outcome": "queried",
              "note": "The learner name in the completion certificate does not match the learner given in the claim. Need to provide the correct certificate for the correct learner."
            }
          },
          {
            "slotID": "4",
            "learnerID": "BF 73 4F 97 L",
            "completionDate": "2024-10-02T11:52:30.850Z",
            "evidenceOfCompletion": "certificate-braxtonSchiller.pdf",
            "evidenceOfCompletionReview": {
              "outcome": "queried",
              "note": "The learner name in the completion certificate does not match the learner given in the claim. Need to provide the correct certificate for the correct learner."
            }
          },
          {
            "slotID": "5",
            "learnerID": "LE 09 5F 94 M",
            "completionDate": "2024-10-02T11:52:30.850Z",
            "evidenceOfCompletion": "certificate-braxtonSchiller.pdf",
            "evidenceOfCompletionReview": {
              "outcome": "queried",
              "note": "The learner name in the completion certificate does not match the learner given in the claim. Need to provide the correct certificate for the correct learner."
            }
          }
        ],
        "sharedCompletionDate": false
      }
    ]
  }
]