[
    {
        "rolename": "Permanent nurse",
        "description": "Nurses in a long-term position that is secured by a contract.",
        "registered": true,
        "eligibility": {
            "isTUeligible": false,
            "isCPDeligible": true
        },
        "distribution": 0.01,
        "jobTitles": ["Staff Nurse", "Registered Nurse (RN)", "Clinical Nurse"]
    },

    {
        "rolename": "Temporary nurse",
        "description": "Nurses employed on temporary/short-term fixed contracts.",
        "registered": true,
        "eligibility": {
            "isTUeligible": false,
            "isCPDeligible": true
        },
        "distribution": 0.01,
        "jobTitles": ["Temporary Staff Nurse", "Contracted Nurse", "Short-Term RN"]
    },

    {
        "rolename": "Bank registered nurse",
        "description": "Nurses who provide cover to cover planned or unplanned workforce shortfalls (e.g. sickness absence, vacancies, annual or maternity leave).",
        "registered": true,
        "eligibility": {
            "isTUeligible": false,
            "isCPDeligible": true
        },
        "distribution": 0.00,
        "jobTitles": ["Bank Nurse", "Casual Registered Nurse", "Cover Nurse"]
    },

    {
        "rolename": "Allied health professional",
        "description": "Allied health professionals supporting health social care/mental health care in settings such as hospitals, schools, care homes, prisons etc.",
        "registered": true,
        "eligibility": {
            "isTUeligible": false,
            "isCPDeligible": true
        },
        "distribution": 0.01,
        "jobTitles": ["Physiotherapist", "Occupational Therapist", "Speech and Language Therapist"]
    },

    {
        "rolename": "Agency staff",
        "description": "Care employees brought in by care providers on short-term contracts to help with periods of short staffing. Require qualifications and competencies to deliver specific roles.",
        "registered": false,
        "eligibility": {
            "isTUeligible": true,
            "isCPDeligible": false
        },
        "distribution": 0.10,
        "jobTitles": ["Care Assistant (Agency)", "Support Worker (Agency)", "Healthcare Assistant (Agency)"]
    },

    {
        "rolename": "Non-regulated managerial",
        "description": "Manager in a non-regulated setting.",
        "registered": false,
        "eligibility": {
            "isTUeligible": true,
            "isCPDeligible": false
        },
        "distribution": 0.10,
        "jobTitles": ["Care Manager", "Service Manager", "Facility Manager"]
    },

    {
        "rolename": "Non-regulated direct care",
        "description": "e.g. Personal Assistant",
        "registered": false,
        "eligibility": {
            "isTUeligible": true,
            "isCPDeligible": false
        },
        "distribution": 0.20,
        "jobTitles": ["Personal Assistant", "Support Worker", "Care Aide"]
    },

    {
        "rolename": "Personal assistants",
        "description": "Someone employed to provide personal and domestic everyday support needed to help people to lead an independent personal and social life at home.",
        "registered": false,
        "eligibility": {
            "isTUeligible": true,
            "isCPDeligible": false
        },
        "distribution": 0.00,
        "jobTitles": ["Personal Care Assistant", "Domestic Support Assistant", "Independent Living Assistant"]
    },

    {
        "rolename": "Direct care",
        "description": "Someone who delivers direct intimate care in any care setting.",
        "registered": false,
        "eligibility": {
            "isTUeligible": true,
            "isCPDeligible": false
        },
        "distribution": 0.37,
        "jobTitles": ["Caregiver", "Healthcare Assistant", "Nursing Assistant"]
    },

    {
        "rolename": "Local authority direct care",
        "description": "Someone who delivers direct intimate care in a local authority setting.",
        "registered": false,
        "eligibility": {
            "isTUeligible": true,
            "isCPDeligible": false
        },
        "distribution": 0.20,
        "jobTitles": ["Local Authority Care Worker", "Council Care Assistant", "Municipal Caregiver"]
    }
]
